{
  "name": "Andre Price",
  "age": 53,
  "address": {
    "street": "Tiope Street",
    "city": "Wizfitpe",
    "state": "ME",
    "zip": "31024"
  },
  "contact": {
    "phone": "(239) 333-2080",
    "servicePhone": "800348155"
  },
  "birthday": "1977-04-22T11:05:53.120Z",
  "ip": "171.50.63.170",
  "foo": "bar",
  "profile": {
    "about": "Hiheju ipnu nelve uzfertu temi bohul pip ceocji lozsorro ebu agogwad seimauke. Ji luvtec vevzib iv nihce nalevicuz uzesihkuz goskiguc eb obucudwa opauwace dag se lejeom hanmibu vojfo coweldu. Ki retwod supsur sihle dutatse gotim mufegoz bewmees jew tukunur mavatum kidob ude iriuz hofga leji jiocumi so. Ak fi em ahapa kuece hosu memku hapovno dothuteb nowi azioke gi fu gor si cebaje.",
    "bio": "Ak rakwad utoipdil karumeaco jigibvil giaw gifac sumija hem juctadpu detzi hat goho av ucjim. Lagu nowo sinaova pefij ticlaep pazuhiku vaoba imitab vihdaz cobmo ev sol dacesocek. Ebhec no fo wum pu rane pisitvaf hiuloow fu rajuz geoj belbugbi. Joep lezmiw esses iweletlu id em eka segkavve jotukuga lejwep ebaam ha gudiwarup me gisifo horune."
  },
  "apiKey": "042fe6149da4b1db7f69d9e98b80443e6ca13efde92d296da3b7f3cc1a8a84ed",
  "currency": {
    "code": "QAR",
    "name": "Qatar Riyal"
  }
}