{
  "name": "Lena Weaver",
  "age": 30,
  "address": {
    "street": "Ogiba Heights",
    "city": "Sikjihdof",
    "state": "AK",
    "zip": "76156"
  },
  "contact": {
    "phone": "(974) 821-6486",
    "servicePhone": "800355327"
  },
  "birthday": "2005-04-01T05:14:16.577Z",
  "ip": "80.141.117.56",
  "foo": "bar",
  "profile": {
    "about": "Vo idfire cigipo zana or epwa hoc juram kilkatkov tahloal sembifron hak arwuacu. Num ukwito uf upuka za ronte niapgev parzadroh on lodag oce nuces ja. Jal umisu zuwuw viad vura hehilma cilov juwpu izuinnab sed ve seh huto.",
    "bio": "Tajabsu kuj otva tugminsal duzhus uzenzip togzeog fulu okimuz ze kerur zehed wezog cini oc ni wi we. Ekeczu mij ted zaecurap viwna gutku co morboh adarihu wedapga betija ze voowa soibiniz hujiti id. Ogison pat mook zi zafinuca vizabcaj biapihe enuota gur maewab vawzi acroh kat penufemo sanvo ufururi rofwud zabvasic. Lomenpa si kacfevmuw wuj buf wuspivvod tusfi baga fodbufub dagemo vimom ake kib kolfarmef vomkeov uzeva cirocdow. Ec aresufot kezo puz ufeud videzze aciho zifnit tolwok soddehcoj zi wo how dafmate tucehjin. Zazhabhoc abufibgaz zehgi ila ev gip ewimbuj dahomza otejavuj firim berpual deplouw dizad hi ba ejtabmor pi."
  },
  "apiKey": "ed5fc05d75c393981610be6fb92be5880c637a9ce6e04b474faa4f4b35f1f664",
  "currency": {
    "code": "KRW",
    "name": "Korea (South) Won"
  }
}