{
  "name": "Florence Rogers",
  "age": 29,
  "address": {
    "street": "Juvij Glen",
    "city": "Kegeut",
    "state": "OH",
    "zip": "49207"
  },
  "contact": {
    "phone": "(630) 586-6988",
    "servicePhone": "800318379"
  },
  "birthday": "1965-04-25T22:43:35.841Z",
  "ip": "30.33.115.41",
  "foo": "bar",
  "profile": {
    "about": "Peliave linleah jonipup feside zak web macihe zi walekivut li iku ocahzu ugiimojud guhob. Ovolaus di hor wuru wevzuru aslubop wi uso nap ivamota kunone kozumtem nogope zur nauc jo zasi. Hobcew fon ozituwo ca lutcud ilisiuv guroh muhaz vedosah kiwofec powugah etkahus sulef uline tin masbafo pitesu.",
    "bio": "Fivnukew vekugwug ejowir ge mucuscol dadoreeji ularu pe zavlu ticer mehjiv taamelih. Cal baloto sab dewus dertif wu he ke faptejwub uhewagim olo bule ciwwobcil pa kahir pupbuk ji wigefiw. Webcile zotik vejen besrorif neh onsedgo folade fizuet dofovobiw ha fujji polekwa ag tebikbu."
  },
  "apiKey": "f55a3474f71c66950ddbe1f5849619a946b6ce9422b18a635791c2ec48580573",
  "currency": {
    "code": "SRD",
    "name": "Suriname Dollar"
  }
}