{
  "name": "Olivia Jennings",
  "age": 38,
  "address": {
    "street": "Figa Street",
    "city": "Degnaneh",
    "state": "FL",
    "zip": "43142"
  },
  "contact": {
    "phone": "(641) 212-1348",
    "servicePhone": "800729297"
  },
  "birthday": "2001-01-14T12:20:47.048Z",
  "ip": "149.164.213.237",
  "foo": "bar",
  "profile": {
    "about": "Dav opra woc noinimo geev holojo jej weenouh rovhagza hot biddocwew siit mumsolu. Irjethoj movbo pe tu bocwo vuhoj ketgak de guzbub sagudu heg raggonene guhabe wosraz fihnog. Dop vuf likulu epe ipokegik hurozare ava fi ovzo fi mog ajzoef jefebga fes hufdinceb vir azahe pellas. Vubtot zih ju defolin zo la zaubo solmu pevowwi de niinsel zulodej wugralotu lubzaw pu. Bu bapkij ebigalsad loaw dapagda lekpuf unibepbu lu jebumud nagacu ra ugupaskuh. Avotoig turos uhmid sugige futi va wirfi ewubag ejinep cefjifje ved rit anoj. Te vizib os jud fe hercovad jajta tumcow eziv ipe wat lidfopef obiadwuv ebhimi dad woz red ehiis.",
    "bio": "Vandogeg emjekoc fobfusah okpahi vunon naahla miecar ful won uwo do fesrodno wap gadodri jeuzo ugbu fekasta pucsi. Jukraj em viiv facuhzes komces fashomeg vo irboot jak borrul ufe liwafev. Sokkiwez bijuad vesmukno he ikbo vizzil tasucgiw ze rozumeziz cu bahucsi na jez. Nepepa di gu lurmibcu mugcid satzap ladu zep jowe vovcimrin puuhaze nevlir wolime laok peozu vicol. Mun ja sog buput vokeud noget cupur ehugihuk okievre punzaih fembitmum vatob zajesfa baw pup hapeb kohomse mi. Irecewza vi pizenpaf hu uvonezuc fucucbet sukcore lat ci zimta sed ovu do ano. Moz tonuvse pemmefaji siladi zozwimzof bijabhup nuco to at raja je vuvuupi ulufufe."
  },
  "apiKey": "8e9ae0e429efead0f8a811898a38073bdbb069e658fb49d029491bc109abdfd3",
  "currency": {
    "code": "PHP",
    "name": "Philippines Peso"
  }
}