{
  "name": "Lee Carroll",
  "age": 63,
  "address": {
    "street": "Bemu Loop",
    "city": "Befvohow",
    "state": "OK",
    "zip": "63849"
  },
  "contact": {
    "phone": "(920) 946-7509",
    "servicePhone": "800382999"
  },
  "birthday": "1961-03-01T14:29:40.958Z",
  "ip": "92.147.31.68",
  "foo": "bar",
  "profile": {
    "about": "Lo waf onmi jah gul iw cocaj wihuj zerwiwpu coeki lob nag otwosiz wu utrur juum ozo. Toceh vujzigtoc pas vawzam ve hu lovegsa mode jami vab oj te mo. Gozmaado bu itkut lif tiplap ida imzemeja ozap ga ga kiuh luj vegsurboc fagpadna sago. Hugju ire ifaehega maduf zozdenzin wogpe wiw hu pukedij ofegeovi acso hetag cewwaweva du tegbunis iju li fut. Zo ahoesaire miz hiwkeew nimefe mib rawfi fihafa rik etwa nud go fi ol. Rapenna ugaho tafja souj ulumu ucofe je anpuzcen sawon no lo wa gele ret ti ni unobulti. Ku femtu uhem uti wugpeso fonefzop kepahuda nemubam pogfug fudsocid urnov kuw no owohud riv tevu.",
    "bio": "Okpub fero ge wupam lu wote evi jumta fo ikfo jukeaba rumudu. Rucfiz sorladzuw gopa zerka ro mad ididul go duhbim pa ah bazi. Pikid ic wo at zen ecicaroma midcame boce nap re daf disfa ubudel fozja uc anesifir. Uma nabikvuk kil ofotuj dunka kimumugi curror apedigwe podhi romisa sifcul kamapi kojbel cunwusju pucbe. Mep iroge kupun ewibib cut mefnewke ti avtalpuw webi zi ciesak tu. Une sima jegisi ose mahoiga wu icioldak fage dezaki vudeja so vizufa be hu fihuruz iv do. Vozna ja fumvitten wa fe jac tik bukziv garme direfavoz reg ruokdoh fav."
  },
  "apiKey": "c63db2dea1c1992c70d18a6f41f2d18b2b072260e05cec792acb5e8763459aef",
  "currency": {
    "code": "VEF",
    "name": "Venezuela Bolivar"
  }
}