{
  "name": "Owen Thompson",
  "age": 59,
  "address": {
    "street": "Dolmem Square",
    "city": "Kuwjusfe",
    "state": "OR",
    "zip": "72315"
  },
  "contact": {
    "phone": "(934) 402-8270",
    "servicePhone": "800999191"
  },
  "birthday": "1995-04-21T22:57:23.240Z",
  "ip": "202.137.230.224",
  "foo": "bar",
  "profile": {
    "about": "Taba cezefo uz ma gubodiz ah cuh use cukti tehpih ra lerojazam cemaj javizlo vevodohi. Lih kiwucwa bokhu fek hef fa le teiba avane zadoku ko dibmeto. Sirit poak ebeeja duci embe wu amo dokibu ahualmef ha rez dukdohol dozdehze zuvsogsa sihnudge jul de. Ha vupvetke pit wivvukros bo gohomlin jod ehiratdon po ib go subowut wusa. Eziapu hivohkec nuhew ke roohes hov tagito ocpize midi cet zajero miraffu miela. Asanapnaf no nezoboaf obpo pufdelri pukib vah eso so fanhobe pe sugof pocgiuh jolpepi valfipnew lepvofer merkodu. Rebok burlolse mekgic eh caneg of wasda diwde etvi lip tehuz omhiid ti zemul vuknir ni pew vaval.",
    "bio": "Famun guzhaw bivoj jo cic ova sulhebna loc no cehioj nikuzgik obokuet defuw id dejfa. Cagonek ata pake vithivin iteok fe nedladic itupuzik lezzap ejegewe uku gi. Fetmon ketajofin iwmeven mosvuj gik je uvsuv me ul imwimsel fijo tutomca co wuwa hokogufi ruezeebe zegec. Vidcu hapvabdop roro dipsak ba ge ponzed ejezoji foisinut usitu rur go imetinmo jimol mujfotcuf zahitufe zin. Bepdub saes zavij lasla jul uju gusviujo muhannez puc ugo erri wijmaf joznuolu kiglet si riuze ucvewbo. Ihuin wa wubdene fot za sajuvoru ucabo iz gif eg em mof."
  },
  "apiKey": "a6db6c8b168469bcd33b039e8ee2f6bab3b915e48a44d85b678cca2345094a77",
  "currency": {
    "code": "NGN",
    "name": "Nigeria Naira"
  }
}